{
  "updated_at": "2026-07-23 00:45 KST",
  "updated_at_iso": "2026-07-23T00:45:40.934113+09:00",
  "next_update": "2026-07-23 17:30 KST",
  "threshold": 15.0,
  "total_scanned": 100,
  "surge_count": 4,
  "market": "해외주식",
  "source": "토스증권 해외주식 거래대금 상위",
  "usd_krw": 1476.1300048828125,
  "stocks": [
    {
      "rank": 62,
      "name": "오틀리 그룹(ADR)",
      "toss_ticker": "",
      "price": "17,928원",
      "change_pct": 34.25,
      "volume": "3,300만원",
      "volume_num": 0.33,
      "ticker": "",
      "country": "정보 없음",
      "country_en": "",
      "ceo": "정보 없음",
      "market_cap": "정보 없음",
      "market_cap_krw": "",
      "sector": "정보 없음",
      "industry": "정보 없음",
      "business_summary": "",
      "short_interest": "정보 없음",
      "short_interest_source": "fintel.io",
      "website": "",
      "exchange": ""
    },
    {
      "rank": 81,
      "name": "큐물러스AI",
      "toss_ticker": "",
      "price": "11,804원",
      "change_pct": 17.47,
      "volume": "2,370만원",
      "volume_num": 0.237,
      "ticker": "",
      "country": "정보 없음",
      "country_en": "",
      "ceo": "정보 없음",
      "market_cap": "정보 없음",
      "market_cap_krw": "",
      "sector": "정보 없음",
      "industry": "정보 없음",
      "business_summary": "",
      "short_interest": "정보 없음",
      "short_interest_source": "fintel.io",
      "website": "",
      "exchange": ""
    },
    {
      "rank": 84,
      "name": "슈퍼 마이크로 컴퓨터",
      "toss_ticker": "",
      "price": "46,673원",
      "change_pct": 24.03,
      "volume": "2,129만원",
      "volume_num": 0.2129,
      "ticker": "",
      "country": "정보 없음",
      "country_en": "",
      "ceo": "정보 없음",
      "market_cap": "정보 없음",
      "market_cap_krw": "",
      "sector": "정보 없음",
      "industry": "정보 없음",
      "business_summary": "",
      "short_interest": "정보 없음",
      "short_interest_source": "fintel.io",
      "website": "",
      "exchange": ""
    },
    {
      "rank": 88,
      "name": "SMCX",
      "toss_ticker": "",
      "price": "14,091원",
      "change_pct": 48.06,
      "volume": "1,859만원",
      "volume_num": 0.1859,
      "ticker": "SMCX",
      "country": "정보 없음",
      "country_en": "",
      "ceo": "정보 없음",
      "market_cap": "정보 없음",
      "market_cap_krw": "",
      "sector": "정보 없음",
      "industry": "정보 없음",
      "business_summary": "이 펀드는 파생 상품, 즉 스왑 계약 및/또는 상장 옵션 계약을 사용하여 기본 증권의 일일 주가 변동률의 2배(200%)를 달성하려고 시도하는 적극적으로 관리되는 상장지수펀드(\"ETF\")입니다. 펀드는 다양화되지 않았습니다.",
      "short_interest": "정보 없음",
      "short_interest_source": "fintel.io",
      "website": "",
      "exchange": "NGM"
    }
  ]
}